agentserve/__init__.py
agentserve/deployment.py
agentserve/logging_config.py
agentserve/models.py
agentserve/utils.py
openai_agentserve-0.0.1.dist-info/LICENSE
openai_agentserve-0.0.1.dist-info/METADATA
openai_agentserve-0.0.1.dist-info/WHEEL
openai_agentserve-0.0.1.dist-info/RECORD
