Metadata-Version: 2.1
Name: openai-agentserve
Version: 0.0.1
Summary: A simple tool to deploy OpenAI Agents as FastAPI web services.
Home-page: https://github.com/superwise-ai/agentserve
License: MIT
Keywords: openai,agents,fastapi,api,web-service
Author: Or Itzahary
Author-email: or.itzary@blattnertech.com
Requires-Python: >=3.11,<3.12
Classifier: Development Status :: 3 - Alpha
Classifier: Intended Audience :: Developers
Classifier: License :: OSI Approved :: MIT License
Classifier: Programming Language :: Python :: 3
Classifier: Programming Language :: Python :: 3.11
Classifier: Topic :: Software Development :: Libraries :: Python Modules
Requires-Dist: fastapi (>=0.100.0,<0.101.0)
Requires-Dist: httpx (>=0.24.0,<0.25.0)
Requires-Dist: openai-agents (>=0.0.5,<0.0.6)
Requires-Dist: uvicorn (>=0.23.0,<0.24.0)
Project-URL: Repository, https://github.com/superwise-ai/agentserve
